{
  "configurations": [
    {
      "name": "x64-Release",
      "generator": "Ninja",
      "configurationType": "Release",
      "buildRoot": "${projectDir}\\out\\build\\${name}",
      "installRoot": "${projectDir}\\out\\install\\${name}",
      "cmakeExecutable": "C:\\zzzzilhan\\programlar\\CMake\\bin\\cmake.exe ",
      "cmakeCommandArgs": "",
      "buildCommandArgs": "",
      "ctestCommandArgs": "",
      "inheritEnvironments": [ "msvc_x64_x64" ]
    },
    {
      "name": "WSL-GCC-Release",
      "generator": "Ninja",
      "configurationType": "Release",
      "buildRoot": "${projectDir}\\out\\build\\${name}",
      "installRoot": "${projectDir}\\out\\install\\${name}",
      "cmakeExecutable": "/snap/bin/cmake",
      "cmakeCommandArgs": "",
      "buildCommandArgs": "",
      "ctestCommandArgs": "",
      "inheritEnvironments": [ "linux_x64" ],
      "wslPath": "C:\\Users\\ciger\\AppData\\Local\\Microsoft\\WindowsApps\\ubuntu.exe"
    },
    {
      "name": "WSL-GCC-Debug",
      "generator": "Ninja",
      "configurationType": "Debug",
      "buildRoot": "${projectDir}\\out\\build\\${name}",
      "installRoot": "${projectDir}\\out\\install\\${name}",
      "cmakeCommandArgs": "",
      "buildCommandArgs": "",
      "ctestCommandArgs": "",
      "inheritEnvironments": [ "linux_x64" ],
      "wslPath": "C:\\Users\\ciger\\AppData\\Local\\Microsoft\\WindowsApps\\ubuntu.exe",
      "cmakeExecutable": "/snap/bin/cmake"
    },
    {
      "name": "x64-Debug",
      "generator": "Ninja",
      "configurationType": "Debug",
      "buildRoot": "${projectDir}\\out\\build\\${name}",
      "installRoot": "${projectDir}\\out\\install\\${name}",
      "cmakeExecutable": "C:\\zzzzilhan\\programlar\\CMake\\bin\\cmake.exe ",
      "cmakeCommandArgs": "",
      "buildCommandArgs": "",
      "ctestCommandArgs": "",
      "inheritEnvironments": [ "msvc_x64_x64" ]
    }
  ]
}